{
  "categories": [
    {
      "id": "cat1",
      "title": "تکنولوژی",
      "description": "مقالات مرتبط با تکنولوژی و فناوری"
    },
    {
      "id": "cat2",
      "title": "برنامه‌نویسی",
      "description": "مقالات مرتبط با برنامه‌نویسی و توسعه نرم‌افزار"
    },
    {
      "id": "cat3",
      "title": "هوش مصنوعی",
      "description": "مقالات مرتبط با هوش مصنوعی و یادگیری ماشین"
    }
  ],
  "articles": [
    {
      "id": "art1",
      "title": "معرفی فریمورک Express.js",
      "content": "اکسپرس (Express.js) یک فریمورک وب مینیمال و انعطاف‌پذیر برای Node.js است که مجموعه‌ای از ویژگی‌های قدرتمند برای وب و اپلیکیشن‌های موبایل ارائه می‌دهد. با استفاده از اکسپرس می‌توانید به راحتی API‌های RESTful و وب‌سایت‌های چندصفحه‌ای بسازید.",
      "image": "/public/1.png",
      "categoryId": "cat2",
      "author": "علی محمدی",
      "createdAt": "2023-01-15T10:30:00.000Z"
    },
    {
      "id": "art2",
      "title": "آشنایی با هوش مصنوعی و کاربردهای آن",
      "content": "هوش مصنوعی (AI) یکی از شاخه‌های علوم کامپیوتر است که به ساخت ماشین‌ها و نرم‌افزارهایی می‌پردازد که قادر به انجام وظایفی هستند که معمولاً به هوش انسانی نیاز دارند. این وظایف شامل یادگیری، استدلال، حل مسئله، درک زبان و تشخیص الگو می‌شود.",
      "image": "/public/2.png",
      "categoryId": "cat3",
      "author": "سارا احمدی",
      "createdAt": "2023-02-20T14:45:00.000Z"
    },
    {
      "id": "art3",
      "title": "معرفی گوشی‌های هوشمند جدید سال 2023",
      "content": "در این مقاله به معرفی جدیدترین گوشی‌های هوشمند سال 2023 می‌پردازیم. این گوشی‌ها با قابلیت‌های جدید و پیشرفته خود، تحولی در دنیای تکنولوژی موبایل ایجاد کرده‌اند.",
      "image": "/public/3.png",
      "categoryId": "cat1",
      "author": "رضا کریمی",
      "createdAt": "2023-03-10T09:15:00.000Z"
    },
    {
      "id": "art4",
      "title": "معرفی گوشی‌های هوشمند جدید سال 2023",
      "content": "در این مقاله به معرفی جدیدترین گوشی‌های هوشمند سال 2023 می‌پردازیم. این گوشی‌ها با قابلیت‌های جدید و پیشرفته خود، تحولی در دنیای تکنولوژی موبایل ایجاد کرده‌اند.",
      "image": "/public/3.png",
      "categoryId": "cat1",
      "author": "رضا کریمی",
      "createdAt": "2023-03-10T09:15:00.000Z"
    },
    {
      "id": "art5",
      "title": "معرفی گوشی‌های هوشمند جدید سال 2023",
      "content": "در این مقاله به معرفی جدیدترین گوشی‌های هوشمند سال 2023 می‌پردازیم. این گوشی‌ها با قابلیت‌های جدید و پیشرفته خود، تحولی در دنیای تکنولوژی موبایل ایجاد کرده‌اند.",
      "image": "/public/5.png",
      "categoryId": "cat1",
      "author": "رضا کریمی",
      "createdAt": "2023-03-10T09:15:00.000Z"
    },
    {
      "id": "7S-N6vmxhE",
      "title": "مقاله تست 1",
      "content": "محتویات مقاله تست ",
      "image": "/public/4.png",
      "categoryId": "cat1",
      "author": "قاسم بساکی",
      "createdAt": "2025-05-21T18:28:58.587Z"
    }
  ],
  "comments": [
    {
      "id": "com1",
      "content": "مقاله بسیار مفیدی بود. ممنون از اشتراک‌گذاری.",
      "articleId": "art1",
      "author": "مهدی حسینی",
      "createdAt": "2023-01-16T08:20:00.000Z"
    },
    {
      "id": "com2",
      "content": "کاش در مورد فریمورک‌های دیگر هم توضیح می‌دادید.",
      "articleId": "art1",
      "author": "زهرا نوری",
      "createdAt": "2023-01-17T11:05:00.000Z"
    },
    {
      "id": "com3",
      "content": "اطلاعات خوبی در مورد هوش مصنوعی ارائه کردید. آیا می‌توانید در مورد یادگیری عمیق هم مطلبی بنویسید؟",
      "articleId": "art2",
      "author": "امیر رضایی",
      "createdAt": "2023-02-21T16:30:00.000Z"
    },
    {
      "id": "com4",
      "content": "به نظر من قیمت این گوشی‌ها خیلی بالاست و ارزش خرید ندارند.",
      "articleId": "art3",
      "author": "حسین محمودی",
      "createdAt": "2023-03-11T10:45:00.000Z"
    }
  ]
}